chaingpt/__init__.py
chaingpt/client.py
chaingpt/exceptions.py
chaingpt/types.py
chaingpt/models/__init__.py
chaingpt/models/auditor.py
chaingpt/models/base.py
chaingpt/models/chat_history.py
chaingpt/models/llm.py
chaingpt/models/news.py
chaingpt/models/nft.py
chaingpt/models/smart_contract.py
chaingpt/services/__init__.py
chaingpt/services/auditor.py
chaingpt/services/base.py
chaingpt/services/llm.py
chaingpt/services/news.py
chaingpt/services/nft.py
chaingpt/services/smart_contract.py
chaingpt/utils/__init__.py
chaingpt/utils/http.py
chaingpt/utils/logger.py
chaingpt-1.1.4.dist-info/licenses/LICENSE.txt
chaingpt-1.1.4.dist-info/METADATA
chaingpt-1.1.4.dist-info/WHEEL
chaingpt-1.1.4.dist-info/top_level.txt
chaingpt-1.1.4.dist-info/RECORD
