Metadata-Version: 2.4
Name: chaingpt
Version: 1.1.4
Summary: Official Python SDK for ChainGPT API - Web3 AI Platform
Author-email: ChainGPT <support@chaingpt.org>
License-Expression: GPL-3.0-or-later
Project-URL: Homepage, https://chaingpt.org
Project-URL: Documentation, https://docs.chaingpt.org/dev-docs-b2b-saas-api-and-sdk/introduction-to-chaingpts-developer-tools
Project-URL: Repository, https://github.com/ChainGPT-org/chaingpt-python
Project-URL: Bug Tracker, https://github.com/ChainGPT-org/chaingpt-python/issues
Keywords: chaingpt,web3,ai,llm,nft,smart-contracts-generator,smart-contracts-audit,ai-crypto-news,blockchain
Classifier: Development Status :: 4 - Beta
Classifier: Intended Audience :: Developers
Classifier: Operating System :: OS Independent
Classifier: Programming Language :: Python :: 3
Classifier: Programming Language :: Python :: 3.9
Classifier: Programming Language :: Python :: 3.10
Classifier: Programming Language :: Python :: 3.11
Classifier: Programming Language :: Python :: 3.12
Classifier: Programming Language :: Python :: 3.13
Classifier: Topic :: Software Development :: Libraries :: Python Modules
Classifier: Topic :: Internet :: WWW/HTTP :: HTTP Servers
Classifier: Topic :: Scientific/Engineering :: Artificial Intelligence
Requires-Python: >=3.9
License-File: LICENSE.txt
Requires-Dist: httpx>=0.28.1
Requires-Dist: pydantic>=2.11.5
Requires-Dist: colorama>=0.4.6
Requires-Dist: python-dotenv>=1.1.0
Requires-Dist: typing-extensions>=4.0.0
Provides-Extra: dev
Requires-Dist: setuptools>=80.9; extra == "dev"
Requires-Dist: twine>=6.1.0; extra == "dev"
Requires-Dist: build>=1.2.2.post1; extra == "dev"
Provides-Extra: test
Requires-Dist: pytest>=8.4.0; extra == "test"
Requires-Dist: pytest-asyncio>=1.0.0; extra == "test"
Requires-Dist: pytest-cov>=6.2.1; extra == "test"
Requires-Dist: pytest-mock>=3.14.1; extra == "test"
Requires-Dist: coverage>=7.9.0; extra == "test"
Requires-Dist: black>=25.1.0; extra == "test"
Requires-Dist: mypy>=1.16.0; extra == "test"
Requires-Dist: flake8>=7.2.0; extra == "test"
Provides-Extra: all
Requires-Dist: chaingpt[dev,test]; extra == "all"
Dynamic: license-file
